Mengko_JYTools/__init__.py
Mengko_JYTools/animation.py
Mengko_JYTools/audio_segment.py
Mengko_JYTools/draft_content_template.json
Mengko_JYTools/draft_folder.py
Mengko_JYTools/effect_segment.py
Mengko_JYTools/exceptions.py
Mengko_JYTools/jianying_controller.py
Mengko_JYTools/keyframe.py
Mengko_JYTools/local_materials.py
Mengko_JYTools/script_file.py
Mengko_JYTools/segment.py
Mengko_JYTools/template_mode.py
Mengko_JYTools/text_segment.py
Mengko_JYTools/time_util.py
Mengko_JYTools/track.py
Mengko_JYTools/util.py
Mengko_JYTools/video_segment.py
Mengko_JYTools/metadata/__init__.py
Mengko_JYTools/metadata/animation_meta.py
Mengko_JYTools/metadata/audio_effect_meta.py
Mengko_JYTools/metadata/effect_meta.py
Mengko_JYTools/metadata/filter_meta.py
Mengko_JYTools/metadata/font_meta.py
Mengko_JYTools/metadata/mask_meta.py
Mengko_JYTools/metadata/transition_meta.py
Mengko_JYTools/metadata/video_effect_meta.py
pyJianYingDraft/__init__.py
pyJianYingDraft/animation.py
pyJianYingDraft/audio_segment.py
pyJianYingDraft/draft_folder.py
pyJianYingDraft/effect_segment.py
pyJianYingDraft/exceptions.py
pyJianYingDraft/jianying_controller.py
pyJianYingDraft/keyframe.py
pyJianYingDraft/local_materials.py
pyJianYingDraft/script_file.py
pyJianYingDraft/segment.py
pyJianYingDraft/template_mode.py
pyJianYingDraft/text_segment.py
pyJianYingDraft/time_util.py
pyJianYingDraft/track.py
pyJianYingDraft/util.py
pyJianYingDraft/video_segment.py
pyJianYingDraft/metadata/__init__.py
pyJianYingDraft/metadata/animation_meta.py
pyJianYingDraft/metadata/audio_effect_meta.py
pyJianYingDraft/metadata/effect_meta.py
pyJianYingDraft/metadata/filter_meta.py
pyJianYingDraft/metadata/font_meta.py
pyJianYingDraft/metadata/mask_meta.py
pyJianYingDraft/metadata/transition_meta.py
pyJianYingDraft/metadata/video_effect_meta.py
mengko_jytools-0.1.0.dist-info/METADATA
mengko_jytools-0.1.0.dist-info/WHEEL
mengko_jytools-0.1.0.dist-info/top_level.txt
mengko_jytools-0.1.0.dist-info/RECORD
