Metadata-Version: 2.4
Name: Mengko_JYTools
Version: 0.1.0
Summary: 剪映草稿文件生成和处理工具
Home-page: https://github.com/Mengko/JYtools
Author: Mengko
Author-email: your_email@example.com
Classifier: Programming Language :: Python :: 3
Classifier: License :: OSI Approved :: MIT License
Classifier: Operating System :: OS Independent
Requires-Python: >=3.6
Dynamic: author
Dynamic: author-email
Dynamic: classifier
Dynamic: description
Dynamic: description-content-type
Dynamic: home-page
Dynamic: requires-python
Dynamic: summary
